Workbook

Sheet Accueil
B2: INJS D'ABIDJAN — RÉFÉRENTIEL EXHAUSTIF DE L'OFFRE DE FORMATION
B4: Institut National de la Jeunesse et des Sports — Abidjan-Marcory, Côte d'Ivoire
B6: Écoles | C6: ENSEPS (STAPS) ; ENSEP (STASE)
B7: Centres rattachés | C7: CNSHN (sport de haut niveau) ; CNMS (médecine du sport)
B8: Cursus | C8: Cursus universitaire (LMD, 5 ans) ; Cycle professionnel (2 ans) ; Formations à la carte
B9: Contenu du classeur | C9: Filières, concours, cycle professionnel, formations à la carte, semestres, grades, et les 4 MAQUETTES COMPLÈTES (UE + ECUE + crédits par semestre) : EM, MS, ES, APA
B11: SOURCES
B12: Sources : site officiel www.injsabidjan.ci (Cursus universitaire, Cycle professionnel, Formation à la carte, Maquettes de formation EM/MS/ES/APA, Futurs étudiants, Notre Institut), plateforme concours.injsabidjan.com, communiqués officiels 2024-2025. Compilation : 28 octobre 2026.
B15: LIMITES (données internes non publiées)
B16: Données internes non publiées : listes nominatives des groupes, maquettes horaires en heures CM/TD/TP, emplois du temps semestriels (plages générales : 8h-12h et 14h-18h, lundi-samedi), maquettes STASE détaillées, effectifs par promotion. À obtenir auprès des scolarités DENSEPS / DENSEP (INJS, Marcory-Abidjan).

Sheet 1. Filières & Concours
A1: 1. LES FILIÈRES DE L'INJS
A3: 1.1. Les 2 grandes filières (mentions)
A4: N° | B4: Filière | C4: Sigle | D4: École | E4: Domaine
A5: 1 | B5: Sciences et Techniques des Activités Physiques et Sportives | C5: STAPS | D5: ENSEPS | E5: Sciences et Technologies
A6: 2 | B6: Sciences et Techniques des Activités Socio-Éducatives | C6: STASE | D6: ENSEP | E6: Sciences de l'Éducation
A8: 1.2. Les 8 filières du cursus universitaire (LMD — 5 ans, accès BAC)
A9: N° | B9: École / Mention | C9: Filière | D9: Sigle | E9: Diplômes délivrés
A10: 1 | B10: ENSEPS (STAPS) | C10: Éducation et Motricité | D10: EM | E10: Licence pro STAPS + Master pro STAPS
A11: 2 | B11: ENSEPS (STAPS) | C11: Management du Sport | D11: MS | E11: Licence pro STAPS + Master pro STAPS
A12: 3 | B12: ENSEPS (STAPS) | C12: Entraînement Sportif | D12: ES | E12: Licence pro STAPS + Master pro STAPS
A13: 4 | B13: ENSEPS (STAPS) | C13: Activités Physiques Adaptées | D13: APA / APAS | E13: Licence pro STAPS + Master pro STAPS
A14: 5 | B14: ENSEP (STASE) | C14: Andragogie | D14: — | E14: Licence pro STASE + Master pro STASE
A15: 6 | B15: ENSEP (STASE) | C15: Loisir | D15: — | E15: Licence pro STASE + Master pro STASE
A16: 7 | B16: ENSEP (STASE) | C16: Entrepreneuriat Jeunesse et Conduite de Projets | D16: ECJP | E16: Licence pro STASE + Master pro STASE
A17: 8 | B17: ENSEP (STASE) | C17: Gérontologie | D17: — | E17: Licence pro STASE + Master pro STASE
A18: 1.3. Concours direct « Professorat de collège » — session 2025 (formations de 3 ans)
A19: Sigle | B19: Concours | C19: Conditions d'accès | D19: Âge | E19: Durée / grade
A20: PC-EPS | B20: Professeur de Collège option Éducation Physique et Sportive | C20: BAC 2021-2025, toutes séries | D20: 18-30 ans | E20: 3 ans (grade Licence)
A21: PC-PS | B21: Professeur de Collège option Sport | C21: BAC 2021-2025 + pratique attestée d'une discipline : Basketball, Football, Handball, Volleyball, Athlétisme, Judo (ceinture noire), Natation, Taekwondo (+ Rugby selon sessions) ; entretien ; pas de tatouage | D21: 18-30 ans | E21: 3 ans (grade Licence)
A22: PC-EP | B22: Professeur de Collège option Éducation Permanente | C22: BAC 2021-2025, toutes séries | D22: 18-30 ans | E22: 3 ans (grade Licence)
A23: PC-EP-ENT | B23: Professeur de Collège option Éducation Permanente spécialité Entrepreneuriat | C23: BAC G2 (2021-2025) OU BAC + BTS Gestion commerciale / Finances-Comptabilité / Transport-Logistique OU BAC + Licence en sciences de gestion | D23: 18-30 ans | E23: 3 ans (grade Licence)

Sheet 2. Cycle professionnel
A1: 2. CYCLE PROFESSIONNEL — 13 cycles de formation (durée : 2 ans)
A2: Destiné aux professionnels en reconversion et aux fonctionnaires visant un grade supérieur.
A4: École | B4: Cycle de formation | C4: Condition d'accès | D4: Durée
A5: ENSEPS | B5: Maîtrise d'EPS | C5: BAC ou diplôme équivalent | D5: 2 ans
A6: ENSEPS | B6: Conseillat d'EPS | C6: CAMEPS + 3 ans d'expérience professionnelle | D6: 2 ans
A7: ENSEPS | B7: Inspectorat Jeunesse et Sport (IJS) | C7: CAPEPS + 3 ans d'expérience OU DECEPS + 5 ans | D7: 2 ans
A8: ENSEPS | B8: Inspectorat Pédagogique (IP) | C8: CAPEPS + 3 ans d'expérience OU DECEPS + 5 ans | D8: 2 ans
A9: ENSEPS | B9: Professorat Professionnel d'EPS | C9: DECEPS + 3 ans d'expérience professionnelle | D9: 2 ans
A10: ENSEPS | B10: Agrégation d'Enseignement Général du Secondaire | C10: CAPEPS + 7 ans d'expérience professionnelle | D10: 2 ans
A11: ENSEP | B11: Maîtrise Adjointe d'EP | C11: BEPC ou diplôme équivalent | D11: 2 ans
A12: ENSEP | B12: Maîtrise d'EP | C12: BAC ou équivalent + 3 ans d'expérience | D12: 2 ans
A13: ENSEP | B13: Inspectorat Jeunesse et Sport option EP | C13: CAPEP + 3 ans OU DECEP + 5 ans d'expérience | D13: 2 ans
A14: ENSEP | B14: Inspectorat Pédagogique EP | C14: CAPEP + 3 ans OU DECEP + 5 ans d'expérience | D14: 2 ans
A15: ENSEP | B15: Conseillat d'EP | C15: CAMEP + 3 ans d'expérience professionnelle | D15: 2 ans
... A17: ENSEP | B17: Agrégation d'Enseignement Général du Secondaire (EP) | C17: CAPEP + 7 ans d'expérience professionnelle | D17: 2 ans

Sheet 3. Formations à la carte
A1: 3. FORMATIONS À LA CARTE — 17 formations (courte/moyenne durée, sans prérequis, certifiantes)
A3: École | B3: Formation | C3: Catégorie
A4: ENSEPS | B4: Moniteur Sportif | C4: Sport
A5: ENSEPS | B5: Officiel de Compétition | C5: Sport
A6: ENSEPS | B6: Entraîneur Fitness | C6: Sport
A7: ENSEPS | B7: Maître Nageur | C7: Sport
A8: ENSEPS | B8: Promoteur d'Événements Sportifs | C8: Management
A9: ENSEPS | B9: Gestionnaire d'Infrastructures Sportives | C9: Gestion
A10: ENSEPS | B10: Garde du Corps | C10: Sécurité
A11: ENSEPS | B11: Fabricant de Matériel Sportif | C11: Artisanat
A12: ENSEP | B12: Photographie | C12: Arts
A13: ENSEP | B13: Peinture | C13: Arts
A14: ENSEP | B14: Entrepreneuriat / Comptabilité | C14: Business
... A20: ENSEP | B20: Art Floral | C20: Arts

Sheet 4. Semestres & Grades
A1: 4. LES SEMESTRES
A3: Palier | B3: Semestres | C3: Crédits/an | D3: Sanction
A4: Licence 1 | B4: S1 + S2 | C4: 60 | D4: —
A5: Licence 2 | B5: S3 + S4 | C5: 60 | D5: —
A6: Licence 3 | B6: S5 + S6 | C6: 60 | D6: Licence professionnelle — 180 crédits (BAC+3)
A7: Master 1 | B7: S7 (M.S1) + S8 (M.S2) | C7: 60 | D7: —
A8: Master 2 | B8: S9 (M.S3) + S10 (M.S4) | C8: 60 | D8: Master professionnel — 120 crédits (BAC+5)
A9: Doctorat 1-3 | B9: S11 à S16 | C9: 180 | D9: Doctorat (BAC+8)
A10: Cycle professionnel | B10: 4 semestres | C10: — | D10: 2 ans par cycle
A11: Professorat de collège (concours) | B11: 6 semestres | C11: — | D11: 3 ans — grade Licence
A13: 7. LES GRADES
A15: Grades universitaires LMD
A16: Grade | B16: Niveau | C16: Crédits | D16: Accès
A17: Licence professionnelle (STAPS / STASE) | B17: BAC+3 | C17: 180 | D17: Concours PC ou filière universitaire
A18: Master professionnel (STAPS / STASE) | B18: BAC+5 | C18: 120 (+180) | D18: Après licence / professorat de lycée
A19: Doctorat (STAPS / STASE — recherche) | B19: BAC+8 | C19: — | D19: Après master
A21: Grades de carrière préparés (cycle professionnel)
A22: Voie EPS : | B22: Maîtrise d'EPS → Professorat professionnel d'EPS (DECEPS) → Professorat certifié (CAPEPS) → Conseillat d'EPS (CAMEPS) → Inspectorat pédagogique / Inspectorat Jeunesse et Sport → Agrégation
A23: Voie EP : | B23: Maîtrise adjointe d'EP → Maîtrise d'EP → Professorat professionnel d'EP (DECEP) → Professorat certifié (CAPEP) → Conseillat d'EP (CAMEP) → Inspectorat pédagogique EP / IJS option EP → Agrégation
A25: Diplômes / certificats : | B25: CAMEPS / CAMEP (Certificat d'Aptitude à la Maîtrise) ; CAPEPS / CAPEP (Certificat d'Aptitude au Professorat) ; DECEPS / DECEP (Diplôme d'Études Certifiées) ; Agrégation de l'enseignement secondaire ; BNS — Brevet National de Secourisme (niveaux 2-3) ; Brevets/diplômes fédéraux d'entraîneur 1, 2, 3 ; Attestation de fin de formation.

Sheet Maquette EM
A1: 11. MAQUETTE « ÉDUCATION ET MOTRICITÉ (EM) » — ENSEPS — filière STAPS
A2: UE = Unité d'Enseignement ; ECUE = Élément Constitutif d'UE ; CECT = crédits. Chaque semestre = 30 crédits.
A4: 🎓 PARCOURS LICENCE
A5: Semestre 1
A6: UE | B6: ECUE (contenu des enseignements) | C6: Crédits CECT/UE
A7: Sciences de la vie et de la santé | B7: ECUE 1 : Anatomie descriptive du squelette appendiculaire ; ECUE 2 : Anatomie fonctionnelle du corps humain | C7: 6
A8: Sciences humaines et sociales | B8: ECUE 1 : Introduction à la psychologie générale ; ECUE 2 : Psychologie de l'apprentissage et du développement | C8: 4
A9: Sciences de l'intervention | B9: Concepts de base en intervention des APS | C9: 2
A10: Initiation aux fondamentaux du football | B10: Football : Fondamentaux | C10: 3
A11: Initiation aux fondamentaux du handball | B11: Handball : Fondamentaux | C11: 3
A12: Initiation aux fondamentaux de la gymnastique | B12: Gymnastique : Fondamentaux | C12: 2
A13: Initiation aux fondamentaux de l'athlétisme | B13: Fondamentaux des courses et des sauts | C13: 3
A14: Spécialisation théorique et pratique dans une APS | B14: APS de spécialité (choix d'un sport de spécialité) | C14: 3
A15: Techniques de communication écrite et orale | B15: ECUE 1 : Étude des styles de rédaction en langue française ; ECUE 2 : Anglais : vocabulaire du sport | C15: 4
B16: TOTAL Semestre 1 | C16: 30
A18: Semestre 2
A19: UE | B19: ECUE (contenu des enseignements) | C19: Crédits CECT/UE
A20: Sciences de la vie et de la santé | B20: ECUE 1 : Physiologie neuromusculaire, métabolisme et APS ; ECUE 2 : Physiologie des grandes fonctions | C20: 6
A21: Sciences humaines et sociales 1 | B21: ECUE 1 : Introduction à la sociologie ; ECUE 2 : Sociologie du jeu et des APS | C21: 4
A22: Initiation aux fondamentaux du rugby | B22: Rugby : Fondamentaux | C22: 3
A23: Initiation aux fondamentaux du basketball | B23: Basketball : Fondamentaux | C23: 3
A24: Initiation aux fondamentaux de la gymnastique II | B24: Gymnastique 2 : fondamentaux | C24: 3
A25: Initiation aux fondamentaux de l'athlétisme II | B25: Fondamentaux des courses de vitesse et des lancers | C25: 3
A26: Spécialisation théorique et pratique dans une APS | B26: APS de spécialité (choix d'un sport de spécialité) | C26: 3
A27: Initiation à l'environnement des TIC | B27: Formation à Microsoft Office Word | C27: 1
A28: Techniques de communication écrite et orale | B28: ECUE 1 : Anglais : communication orale (People and places) ; ECUE 2 : Français : expression orale et prise de parole en public | C28: 4
B29: TOTAL Semestre 2 | C29: 30
A31: Semestre 3
A32: UE | B32: ECUE (contenu des enseignements) | C32: Crédits CECT/UE
A33: Sciences de la vie et de la santé | B33: ECUE 1 : Nutrition et APS ; ECUE 2 : Biomécanique du geste | C33: 4
A34: Sciences humaines et sociales appliquées aux APS | B34: Histoire du sport : naissance et développement du sport moderne | C34: 2
A35: Connaissances institutionnelles du sport | B35: Connaissances institutionnelles et législatives de l'organisation du sport | C35: 2
A36: Initiation aux fondamentaux du volleyball | B36: Volleyball : Fondamentaux | C36: 3
A37: Initiation aux sports de combat de préhension | B37: Judo : Fondamentaux ; Lutte : Fondamentaux | C37: 2
A38: Initiation aux sports de combat de percussion | B38: Boxe : Fondamentaux ; Taekwondo : Fondamentaux | C38: 2
A39: Initiation aux sports d'entretien et santé | B39: Fitness et Conditionnement physique | C39: 2
A40: Matérialisation des plateaux de pratique des APS et performance | B40: Techniques de traçage des aires de pratique sportive et utilisation des instruments de mesure de la performance | C40: 3
A41: Spécialisation théorique et pratique dans une APS | B41: APS de spécialité (choix d'un sport de spécialité) | C41: 3
A42: Pré-professionnalisation | B42: Stage pédagogique au primaire : animation sportive 1re étape | C42: 3
A43: Techniques d'expression écrite et orale | B43: ECUE 1 : Anglais : communication orale (People and places : sport) ; ECUE 2 : Français : expression orale et prise de parole en public | C43: 4
B44: TOTAL Semestre 3 | C44: 30
A46: Semestre 4
A47: UE | B47: ECUE (contenu des enseignements) | C47: Crédits CECT/UE
A48: Connaissances institutionnelles des systèmes éducatifs | B48: ECUE 1 : Structure et fonctionnement du système éducatif ivoirien ; ECUE 2 : Histoire de l'EPS : courants pédagogiques | C48: 4
A49: Intervention en APS | B49: ECUE 1 : Apprentissages moteurs ; ECUE 2 : Conception et planification de séance en animation sportive au primaire | C49: 4
A50: Aspects pédagogiques du football | B50: Pédagogie du football : familiarisation et initiation | C50: 3
A51: Aspects pédagogiques du handball | B51: Pédagogie du handball : familiarisation et initiation | C51: 3
A52: Aspects pédagogiques des sports d'expression corporelle | B52: Pédagogie de la gymnastique : familiarisation et initiation | C52: 3
A53: Aspects pédagogiques de l'athlétisme | B53: Pédagogie de l'athlétisme : familiarisation et initiation | C53: 3
A54: Spécialisation théorique et pratique dans une APS | B54: APS de spécialité | C54: 2
A55: Pré-professionnalisation | B55: Stage pédagogique au primaire : animation sportive 2e étape | C55: 3
A56: Méthodologie et outils | B56: Introduction à la méthodologie de la recherche scientifique : projet de recherche | C56: 3
A57: Techniques d'expression écrite et orale | B57: Anglais : communication orale (People and places : sport) 2 | C57: 2
B58: TOTAL Semestre 4 | C58: 30
A60: Semestre 5
A61: UE | B61: ECUE (contenu des enseignements) | C61: Crédits CECT/UE
A62: Intervention en APS | B62: Conception et planification de l'enseignement de l'EPS au secondaire | C62: 3
A63: Aspects pédagogiques du handball | B63: Pédagogie du handball : familiarisation et initiation | C63: 3
A64: Aspects pédagogiques du basketball | B64: Pédagogie du basketball : familiarisation et initiation | C64: 3
A65: Aspects pédagogiques du rugby | B65: Pédagogie du rugby : familiarisation et initiation | C65: 3
A66: Aspects pédagogiques du volleyball | B66: Pédagogie du volleyball : familiarisation | C66: 3
A67: Aspects pédagogiques de l'athlétisme | B67: Pédagogie de l'athlétisme : familiarisation et initiation | C67: 3
A68: Spécialisation théorique et pratique dans une APS | B68: APS de spécialité | C68: 3
A69: Aspects pédagogiques du football | B69: Pédagogie du football : familiarisation et initiation | C69: 2
A70: Méthodologie | B70: Initiation à la méthodologie de la recherche scientifique : cadre méthodologique | C70: 3
A71: Life Skills | B71: ECUE 1 : Adolescence : éthique et morale en milieu scolaire ; ECUE 2 : Culture civique | C71: 2
A72: Techniques d'expression écrite et orale | B72: Anglais : communication orale | C72: 2
B73: TOTAL Semestre 5 | C73: 30
A75: Semestre 6
A76: UE | B76: ECUE (contenu des enseignements) | C76: Crédits CECT/UE
A77: Intervention en APS : interaction | B77: Analyse des variables de l'interaction en EPS | C77: 2
A78: Intervention en APS : mesure et évaluation | B78: Application des théories de mesure et évaluation en EPS | C78: 2
A79: Aspects pédagogiques du volleyball | B79: Pédagogie du volleyball : initiation | C79: 3
A80: Aspects pédagogiques de la gymnastique | B80: Pédagogie de la gymnastique : initiation | C80: 2
A81: Aspects pédagogiques de l'athlétisme | B81: Pédagogie de l'athlétisme : initiation | C81: 3
A82: Aspects pédagogiques du basketball | B82: Pédagogie du basketball : familiarisation et initiation | C82: 3
A83: Aspects pédagogiques du rugby | B83: Pédagogie du rugby : familiarisation et initiation | C83: 3
A84: Spécialisation théorique et pratique dans une APS | B84: Théorie et pratique de l'entraînement de l'APS de spécialité | C84: 2
A85: Traumatologie du sport | B85: Étude des pathologies liées à la pratique du sport et leurs traitements | C85: 2
A86: Pré-professionnalisation | B86: Stage pédagogique dans un établissement d'enseignement secondaire | C86: 3
A87: Formation à la recherche scientifique | B87: Séminaire de recherche : élaboration de projet de mémoire | C87: 3
A88: Techniques d'expression écrite et orale | B88: Anglais : communication orale | C88: 2
B89: TOTAL Semestre 6 | C89: 30
A91: TOTAL LICENCE : 180 crédits
A93: 🎓 PARCOURS MASTER
A94: Semestre 1 (M1/S7)
A95: UE | B95: ECUE (contenu des enseignements) | C95: Crédits CECT/UE
A96: Connaissances institutionnelles de l'éducation et du sport | B96: Systèmes éducatifs : réalités scolaires, éducatives et dispositifs institutionnels | C96: 3
A97: Connaissances psychosociologiques des APS | B97: Aspects psychosociologiques des APS | C97: 3
A98: Intervention en mesure et évaluation de l'EPS | B98: Mesure et évaluation de l'EPS | C98: 3
A99: Didactique de l'EPS | B99: Didactique de l'EPS : conception et analyse des situations d'enseignement-apprentissage | C99: 3
A100: Didactique des sports d'expression corporelle | B100: Didactique de la gymnastique | C100: 3
A101: Didactique des sports collectifs de petit terrain | B101: ECUE 1 : Didactique du handball ; ECUE 2 : Didactique du basketball | C101: 6
A102: Méthodologie | B102: Méthodologie de la recherche scientifique 1 | C102: 3
A103: Formation à la recherche | B103: Séminaire de recherche en Éducation et Motricité | C103: 4
A104: Technique d'expression écrite et orale | B104: Anglais professionnel | C104: 2
B105: TOTAL Semestre 1 (M1/S7) | C105: 30
A107: Semestre 2 (M1/S8)
A108: UE | B108: ECUE (contenu des enseignements) | C108: Crédits CECT/UE
A109: Connaissances psychologiques des APS | B109: Gestion des émotions et stratégies de motivation dans la conduite des séances d'EPS | C109: 2
...

Sheet Maquette MS
A1: 11. MAQUETTE « MANAGEMENT DU SPORT (MS) » — ENSEPS — filière STAPS
A2: UE = Unité d'Enseignement ; ECUE = Élément Constitutif d'UE ; CECT = crédits. Chaque semestre = 30 crédits.
A4: 🎓 PARCOURS LICENCE
A5: Semestre 1
A6: UE | B6: ECUE (contenu des enseignements) | C6: Crédits CECT/UE
A7: Sciences de la vie et de la santé | B7: ECUE 1 : Anatomie descriptive du squelette appendiculaire ; ECUE 2 : Anatomie fonctionnelle du corps humain | C7: 6
A8: Sciences humaines et sociales | B8: ECUE 1 : Introduction à la psychologie générale ; ECUE 2 : Psychologie de l'apprentissage et du développement | C8: 4
A9: Sciences de l'intervention | B9: Concepts de base en intervention des APS | C9: 2
A10: Initiation aux fondamentaux du football | B10: Football : Fondamentaux | C10: 3
A11: Initiation aux fondamentaux du handball | B11: Handball : Fondamentaux | C11: 3
A12: Initiation aux fondamentaux de la gymnastique | B12: Gymnastique : Fondamentaux | C12: 2
A13: Initiation aux fondamentaux de l'athlétisme | B13: Fondamentaux des courses et des sauts | C13: 3
A14: Spécialisation théorique et pratique dans une APS | B14: APS de spécialité (choix d'un sport de spécialité) | C14: 3
A15: Techniques de communication écrite et orale | B15: ECUE 1 : Étude des styles de rédaction en langue française ; ECUE 2 : Anglais : vocabulaire du sport | C15: 4
B16: TOTAL Semestre 1 | C16: 30
A18: Semestre 2
A19: UE | B19: ECUE (contenu des enseignements) | C19: Crédits CECT/UE
A20: Sciences de la vie et de la santé | B20: ECUE 1 : Physiologie neuromusculaire, métabolisme et APS ; ECUE 2 : Physiologie des grandes fonctions | C20: 6
A21: Sciences humaines et sociales 1 | B21: ECUE 1 : Introduction à la sociologie ; ECUE 2 : Sociologie du jeu et des APS | C21: 4
A22: Initiation aux fondamentaux du rugby | B22: Rugby : Fondamentaux | C22: 3
A23: Initiation aux fondamentaux du basketball | B23: Basketball : Fondamentaux | C23: 3
A24: Initiation aux fondamentaux de la gymnastique II | B24: Gymnastique 2 : fondamentaux | C24: 3
A25: Initiation aux fondamentaux de l'athlétisme II | B25: Fondamentaux des courses de vitesse et des lancers | C25: 3
A26: Spécialisation théorique et pratique dans une APS | B26: APS de spécialité (choix d'un sport de spécialité) | C26: 3
A27: Initiation à l'environnement des TIC | B27: Formation à Microsoft Office Word | C27: 1
A28: Techniques de communication écrite et orale | B28: ECUE 1 : Anglais : communication orale (People and places) ; ECUE 2 : Français : expression orale et prise de parole en public | C28: 4
B29: TOTAL Semestre 2 | C29: 30
A31: Semestre 3
A32: UE | B32: ECUE (contenu des enseignements) | C32: Crédits CECT/UE
A33: Sciences de la vie et de la santé | B33: ECUE 1 : Nutrition et APS ; ECUE 2 : Biomécanique du geste | C33: 4
A34: Sciences humaines et sociales appliquées aux APS | B34: Histoire du sport : naissance et développement du sport moderne | C34: 2
A35: Connaissances institutionnelles du sport | B35: Connaissances institutionnelles et législatives de l'organisation du sport | C35: 2
A36: Initiation aux fondamentaux du volleyball | B36: Volleyball : Fondamentaux | C36: 3
A37: Initiation aux sports de combat de préhension | B37: Judo : Fondamentaux ; Lutte : Fondamentaux | C37: 2
A38: Initiation aux sports de combat de percussion | B38: Boxe : Fondamentaux ; Taekwondo : Fondamentaux | C38: 2
A39: Initiation aux sports d'entretien et santé | B39: Fitness et Conditionnement physique | C39: 2
A40: Matérialisation des plateaux de pratique des APS et performance | B40: Techniques de traçage des aires de pratique sportive et utilisation des instruments de mesure de la performance | C40: 3
A41: Spécialisation théorique et pratique dans une APS | B41: APS de spécialité (choix d'un sport de spécialité) | C41: 3
A42: Pré-professionnalisation | B42: Stage pédagogique au primaire : animation sportive 1re étape | C42: 3
A43: Techniques d'expression écrite et orale | B43: ECUE 1 : Anglais : communication orale (People and places : sport) ; ECUE 2 : Français : expression orale et prise de parole en public | C43: 4
B44: TOTAL Semestre 3 | C44: 30
A46: Semestre 4
A47: UE | B47: ECUE (contenu des enseignements) | C47: Crédits CECT/UE
A48: Connaissances institutionnelles du sport | B48: Organisation et réglementation en sport, loisirs et tourisme sportif | C48: 2
A49: Connaissances juridiques des entreprises sportives | B49: ECUE 1 : Introduction au droit ; ECUE 2 : Droit et législation du travail et des associations sportives | C49: 4
A50: Économie et marketing du sport | B50: ECUE 1 : Comptabilité et gestions financières ; ECUE 2 : Introduction à l'économie et économie du sport | C50: 6
A51: Management et gestion du sport | B51: ECUE 1 : Introduction au marketing ; ECUE 2 : Management d'équipe et gestion des ressources humaines | C51: 6
A52: Gestion et entretien des infrastructures sportives | B52: Gestion et aménagement des infrastructures et équipements | C52: 2
A53: Spécialisation théorique et pratique dans une APS | B53: APS de spécialité | C53: 2
A54: Pré-professionnalisation | B54: Conduite d'action professionnelle en observation (stage) | C54: 2
A55: Méthodologie de la recherche | B55: Introduction à la méthodologie de la recherche scientifique | C55: 3
A56: Technologie de l'information et de la communication | B56: Initiation à l'informatique et aux techniques de montage audiovisuel : APS et activité récréative | C56: 1
A57: Techniques d'expression écrite et orale | B57: Anglais spécifique au management : gestion des organisations sportives | C57: 2
B58: TOTAL Semestre 4 | C58: 30
A60: Semestre 5
A61: UE | B61: ECUE (contenu des enseignements) | C61: Crédits CECT/UE
A62: Connaissances sociologiques et managériales du sport | B62: ECUE 1 : Sociologie des organisations sportives ; ECUE 2 : Management des organisations sportives | C62: 4
A63: Droit du sport | B63: ECUE 1 : Cadre institutionnel et législatif du sport en Côte d'Ivoire ; ECUE 2 : Sécurité de l'installation sportive et droit de la responsabilité | C63: 4
A64: Management et marketing stratégique | B64: Étude de marché | C64: 2
A65: Stratégie de communication | B65: Concepts, techniques et stratégies de communication des organisations sportives | C65: 2
A66: Finance et comptabilité du sport | B66: ECUE 1 : Analyse financière et fiscalité des organisations sportives ; ECUE 2 : Analyse des modes de financement du sport | C66: 4
A67: Spécialisation théorique et pratique dans une APS | B67: APS de spécialité | C67: 3
A68: Pratique de l'événementiel sportif | B68: ECUE 1 : Management de projet : événement sportif de la planification à la clôture 1 ; ECUE 2 : idem 2 | C68: 4
A69: Méthodologie de la recherche | B69: Initiation à la méthodologie de la recherche scientifique 3 | C69: 2
A70: Technologie de l'information et de la communication | B70: Introduction à l'informatique : prise en main d'Excel | C70: 2
A71: Technique d'expression orale et écrite | B71: Anglais en marketing et management du sport | C71: 2
A72: Life Skills | B72: Culture civique | C72: 1
B73: TOTAL Semestre 5 | C73: 30
A75: Semestre 6
A76: UE | B76: ECUE (contenu des enseignements) | C76: Crédits CECT/UE
A77: Gestion de l'environnement sportif | B77: ECUE 1 : Réglementation et responsabilité en matière de risques et assurances sportives ; ECUE 2 : Aménagement des territoires sportifs : conception et gestion prospective des équipements sportifs | C77: 6
A78: Marketing et économie du sport | B78: ECUE 1 : Stratégie marketing : conception de produits et services de loisir sportif ; ECUE 2 : Sport, loisirs et développement durable : analyse socio-économique | C78: 6
A79: Pratique de l'entrepreneuriat et de l'événementiel sportif | B79: Entrepreneuriat sportif : création de services/entreprises sportives (MS, APAS) | C79: 2
A80: Gestion administrative du sport | B80: ECUE 1 : Administration publique de CI : attributions, organisation et fonctionnement du ministère des Sports ; ECUE 2 : Élaboration et gestion de projet dans le domaine sportif (GAR) | C80: 4
A81: Fonction publique | B81: Droits et obligations du fonctionnaire | C81: 2
A82: Spécialisation pratique et théorique dans une APS | B82: APS de spécialité | C82: 2
A83: Pré-professionnalisation | B83: Conduite et présentation d'action professionnelle en responsabilité (stage) | C83: 3
A84: Formation à la recherche scientifique | B84: Séminaire de recherche : élaboration de projet de mémoire | C84: 3
A85: Technique d'expression écrite et orale | B85: Anglais en organisation d'événements sportifs | C85: 2
B86: TOTAL Semestre 6 | C86: 30
A88: TOTAL LICENCE : 180 crédits
A90: 🎓 PARCOURS MASTER
A91: Semestre 1 (M1/S7)
A92: UE | B92: ECUE (contenu des enseignements) | C92: Crédits CECT/UE
A93: Aspects fondamentaux de la gestion | B93: ECUE 1 : Événementiel sportif : stratégies de communication des organisations sportives ; ECUE 2 : Marketing des services : publics associatifs et commerciaux | C93: 4
A94: Analyse stratégique | B94: ECUE 1 : Étude de cas marketing : le marché des produits et services de sport et loisirs ; ECUE 2 : Étude de cas : analyse et évaluation de l'action publique | C94: 6
A95: Gestion publique | B95: Rédaction administrative et techniques de conduite de réunion | C95: 3
A96: Finances publiques | B96: Analyse des procédures d'exécution du budget | C96: 2
A97: Professionnalisation | B97: Stage professionnel dans une structure du Ministère des Sports : élaboration d'un projet | C97: 4
A98: Spécialisation théorique et pratique dans une APS | B98: APS de spécialité | C98: 3
A99: Théorie de la méthodologie de la recherche | B99: Méthodologie de la recherche scientifique 2 : conception des instruments de collecte de données | C99: 3
A100: Formation à la recherche | B100: Séminaire de recherche en management du sport | C100: 3
A101: Technique d'expression écrite et orale | B101: Anglais professionnel | C101: 2
B102: TOTAL Semestre 1 (M1/S7) | C102: 30
A104: Semestre 2 (M1/S8)
A105: Non détaillé distinctement sur la page officielle (coquille du site INJS).
A106: Semestre 3 (M2/S9)
A107: UE | B107: ECUE (contenu des enseignements) | C107: Crédits CECT/UE
A108: Professionnalisation | B108: Stage milieu professionnel | C108: 15
A109: Formation à la recherche | B109: Séminaire de recherche 3 | C109: 7
...

Sheet Maquette ES
A1: 11. MAQUETTE « ENTRAÎNEMENT SPORTIF (ES) » — ENSEPS — filière STAPS
A2: UE = Unité d'Enseignement ; ECUE = Élément Constitutif d'UE ; CECT = crédits. Chaque semestre = 30 crédits.
A4: 🎓 PARCOURS LICENCE
A5: Semestre 1
A6: UE | B6: ECUE (contenu des enseignements) | C6: Crédits CECT/UE
A7: Sciences de la vie et de la santé | B7: ECUE 1 : Anatomie descriptive du squelette appendiculaire ; ECUE 2 : Anatomie fonctionnelle du corps humain | C7: 6
A8: Sciences humaines et sociales | B8: ECUE 1 : Introduction à la psychologie générale ; ECUE 2 : Psychologie de l'apprentissage et du développement | C8: 4
A9: Sciences de l'intervention | B9: Concepts de base en intervention des APS | C9: 2
A10: Initiation aux fondamentaux du football | B10: Football : Fondamentaux | C10: 3
A11: Initiation aux fondamentaux du handball | B11: Handball : Fondamentaux | C11: 3
A12: Initiation aux fondamentaux de la gymnastique | B12: Gymnastique : Fondamentaux | C12: 2
A13: Initiation aux fondamentaux de l'athlétisme | B13: Fondamentaux des courses et des sauts | C13: 3
A14: Spécialisation théorique et pratique dans une APS | B14: APS de spécialité (choix d'un sport de spécialité) | C14: 3
A15: Techniques de communication écrite et orale | B15: ECUE 1 : Étude des styles de rédaction en langue française ; ECUE 2 : Anglais : vocabulaire du sport | C15: 4
B16: TOTAL Semestre 1 | C16: 30
A18: Semestre 2
A19: UE | B19: ECUE (contenu des enseignements) | C19: Crédits CECT/UE
A20: Sciences de la vie et de la santé | B20: ECUE 1 : Physiologie neuromusculaire, métabolisme et APS ; ECUE 2 : Physiologie des grandes fonctions | C20: 6
A21: Sciences humaines et sociales 1 | B21: ECUE 1 : Introduction à la sociologie ; ECUE 2 : Sociologie du jeu et des APS | C21: 4
A22: Initiation aux fondamentaux du rugby | B22: Rugby : Fondamentaux | C22: 3
A23: Initiation aux fondamentaux du basketball | B23: Basketball : Fondamentaux | C23: 3
A24: Initiation aux fondamentaux de la gymnastique II | B24: Gymnastique 2 : fondamentaux | C24: 3
A25: Initiation aux fondamentaux de l'athlétisme II | B25: Fondamentaux des courses de vitesse et des lancers | C25: 3
A26: Spécialisation théorique et pratique dans une APS | B26: APS de spécialité (choix d'un sport de spécialité) | C26: 3
A27: Initiation à l'environnement des TIC | B27: Formation à Microsoft Office Word | C27: 1
A28: Techniques de communication écrite et orale | B28: ECUE 1 : Anglais : communication orale (People and places) ; ECUE 2 : Français : expression orale et prise de parole en public | C28: 4
B29: TOTAL Semestre 2 | C29: 30
A31: Semestre 3
A32: UE | B32: ECUE (contenu des enseignements) | C32: Crédits CECT/UE
A33: Sciences de la vie et de la santé | B33: ECUE 1 : Nutrition et APS ; ECUE 2 : Biomécanique du geste | C33: 4
A34: Sciences humaines et sociales appliquées aux APS | B34: Histoire du sport : naissance et développement du sport moderne | C34: 2
A35: Connaissances institutionnelles du sport | B35: Connaissances institutionnelles et législatives de l'organisation du sport | C35: 2
A36: Initiation aux fondamentaux du volleyball | B36: Volleyball : Fondamentaux | C36: 3
A37: Initiation aux sports de combat de préhension | B37: Judo : Fondamentaux ; Lutte : Fondamentaux | C37: 2
A38: Initiation aux sports de combat de percussion | B38: Boxe : Fondamentaux ; Taekwondo : Fondamentaux | C38: 2
A39: Initiation aux sports d'entretien et santé | B39: Fitness et Conditionnement physique | C39: 2
A40: Matérialisation des plateaux de pratique des APS et performance | B40: Techniques de traçage des aires de pratique sportive et utilisation des instruments de mesure de la performance | C40: 3
A41: Spécialisation théorique et pratique dans une APS | B41: APS de spécialité (choix d'un sport de spécialité) | C41: 3
A42: Pré-professionnalisation | B42: Stage pédagogique au primaire : animation sportive 1re étape | C42: 3
A43: Techniques d'expression écrite et orale | B43: ECUE 1 : Anglais : communication orale (People and places : sport) ; ECUE 2 : Français : expression orale et prise de parole en public | C43: 4
B44: TOTAL Semestre 3 | C44: 30
A46: Semestre 4
A47: UE | B47: ECUE (contenu des enseignements) | C47: Crédits CECT/UE
A48: Facteurs biologiques de la performance | B48: ECUE 1 : Déterminants physiologiques de la performance sportive ; ECUE 2 : Déterminants biomécaniques de la performance sportive | C48: 4
A49: Facteurs psychosociologiques de la performance | B49: Déterminants psychologiques de la performance sportive | C49: 2
A50: Développement des qualités physiques | B50: ECUE 1 : Techniques de développement des qualités physiques 1 : vitesse, coordination et endurance ; ECUE 2 : idem 2 : force | C50: 4
A51: Formation au métier d'entraîneur 1 | B51: Préparation du diplôme fédéral d'entraîneur 1 (pédagogie des 8-12 ans) | C51: 3
A52: Spécialisation théorique et pratique dans une APS | B52: Théorie et pratique de l'entraînement de l'APS de spécialité | C52: 2
A53: Pratique des APS et entraînement | B53: Méthodologie de l'entraînement sportif 1 | C53: 3
A54: Pré-professionnalisation | B54: Stage d'entraîneur dans une structure sportive | C54: 4
A55: Technologie de l'information et de la communication | B55: Initiation à l'informatique et application à l'analyse de la performance sportive | C55: 3
A56: Méthodologie de la recherche | B56: Introduction à la méthodologie de la recherche scientifique | C56: 3
A57: Technique de communication écrite et orale | B57: Anglais spécifique à l'entraînement sportif | C57: 2
B58: TOTAL Semestre 4 | C58: 30
A60: Semestre 5
A61: UE | B61: ECUE (contenu des enseignements) | C61: Crédits CECT/UE
A62: Management des fédérations sportives | B62: Management des fédérations sportives nationales 1 | C62: 2
A63: Droit et sport de haut niveau | B63: Cadre institutionnel et législatif du sport en Côte d'Ivoire | C63: 2
A64: Pratique des APS et entraînement sportif | B64: ECUE 1 : Techniques de développement des qualités physiques 3 : étirements, relaxations et massages ; ECUE 2 : idem 4 : musculation sans charge et avec charge (force) | C64: 4
A65: Formation au métier d'entraîneur 2 | B65: Préparation du diplôme fédéral d'entraîneur 2 (méthodes d'entraînement spécifique) | C65: 3
A66: Spécialisation théorique et pratique dans une APS | B66: Théorie et pratique de l'entraînement de l'APS de spécialité | C66: 5
A67: Entraînement et performance sportive | B67: ECUE 1 : Méthodologie de l'entraînement sportif 2 ; ECUE 2 : Intégration des facteurs de la performance sportive | C67: 6
A68: Brevet National de Secourisme | B68: Préparation au BNS niveau 3 | C68: 2
A69: Méthodologie de la recherche | B69: Initiation à la méthodologie de la recherche scientifique : élaboration de projet de recherche | C69: 2
A70: Technique d'expression écrite et orale | B70: Anglais spécifique à l'entraînement sportif | C70: 2
A71: Life Skills | B71: ECUE 1 : Adolescence : éthique et morale en milieu sportif ; ECUE 2 : Culture civique | C71: 2
B72: TOTAL Semestre 5 | C72: 30
A74: Semestre 6
A75: UE | B75: ECUE (contenu des enseignements) | C75: Crédits CECT/UE
A76: Management des fédérations sportives | B76: Management des fédérations sportives nationales 2 | C76: 2
A77: Nutrition du sportif | B77: Diététique et nutrition appliquées à l'entraînement sportif | C77: 2
A78: Management de la compétition | B78: Préparation mentale et coaching d'athlètes en compétition | C78: 3
A79: Pratique des APS et entraînement sportif | B79: ECUE 1 : Techniques d'analyse de la performance sportive ; ECUE 2 : Méthodologie de l'entraînement sportif 3 | C79: 4
A80: Formation au métier d'entraîneur 3 | B80: Préparation du diplôme fédéral d'entraîneur 3 (méthodes d'entraînement cognitives et psychologiques) | C80: 3
A81: Spécialisation théorique et pratique dans une APS | B81: Théorie et pratique de l'entraînement de l'APS de spécialité | C81: 4
A82: Réathlétisation des athlètes | B82: Prise en charge d'athlètes en fatigue, surentraînement, blessure et récupération | C82: 3
A83: Pré-professionnalisation | B83: Stage d'entraînement dans une fédération sportive | C83: 4
A84: Formation à la recherche scientifique | B84: Séminaire de recherche : élaboration de projet de mémoire | C84: 3
A85: Technique d'expression écrite et orale | B85: Anglais spécifique à l'entraînement sportif | C85: 2
B86: TOTAL Semestre 6 | C86: 30
A88: TOTAL LICENCE : 180 crédits
A90: 🎓 PARCOURS MASTER
A91: Semestre 1 (M1/S7)
A92: UE | B92: ECUE (contenu des enseignements) | C92: Crédits CECT/UE
A93: Sciences humaines et performance sportive | B93: Déterminants sociologiques de la performance sportive | C93: 2
A94: Optimisation de la performance | B94: Évaluation des qualités physiques et facteurs limitants (endurance, puissance, équilibre, coordination) | C94: 3
A95: Construction et mise en œuvre du projet de performance | B95: ECUE 1 : Détecter, sélectionner et former des sportifs de haut niveau ; ECUE 2 : Planification et régulation des composantes de la performance sur la saison | C95: 6
A96: Formation à l'entraînement | B96: Préparation au brevet fédéral d'entraîneur 1 | C96: 4
A97: Spécialisation théorique et pratique dans une APS | B97: APS de spécialité | C97: 5
A98: Méthodologie de la recherche : aspects théoriques | B98: Conception d'instruments de collecte de données | C98: 4
A99: Formation à la recherche | B99: Séminaire de recherche en entraînement sportif | C99: 4
A100: Technique d'expression écrite et orale | B100: Anglais professionnel | C100: 2
B101: TOTAL Semestre 1 (M1/S7) | C101: 30
A103: Semestre 2 (M1/S8)
A104: UE | B104: ECUE (contenu des enseignements) | C104: Crédits CECT/UE
A105: Adaptation à l'exercice | B105: ECUE 1 : Adaptation cardiovasculaire à l'exercice ; ECUE 2 : Traumatologie du sport 2 | C105: 4
A106: Spécialisation théorique et pratique dans une APS | B106: APS de spécialité | C106: 3
A107: Formation à l'entraînement | B107: Préparation au brevet fédéral d'entraîneur 2 | C107: 3
A108: Secourisme | B108: Préparation au Brevet National de Secourisme 2 | C108: 2
A109: Formation professionnelle | B109: Stage professionnel dans un club sportif : élaboration d'un projet | C109: 5
...

Sheet Maquette APA
A1: 11. MAQUETTE « ACTIVITÉS PHYSIQUES ADAPTÉES (APA) » — ENSEPS — filière STAPS
A2: UE = Unité d'Enseignement ; ECUE = Élément Constitutif d'UE ; CECT = crédits. Chaque semestre = 30 crédits.
A4: 🎓 PARCOURS LICENCE
A5: Semestre 1
A6: UE | B6: ECUE (contenu des enseignements) | C6: Crédits CECT/UE
A7: Sciences de la vie et de la santé | B7: ECUE 1 : Anatomie descriptive du squelette appendiculaire ; ECUE 2 : Anatomie fonctionnelle du corps humain | C7: 6
A8: Sciences humaines et sociales | B8: ECUE 1 : Introduction à la psychologie générale ; ECUE 2 : Psychologie de l'apprentissage et du développement | C8: 4
A9: Sciences de l'intervention | B9: Concepts de base en intervention des APS | C9: 2
A10: Initiation aux fondamentaux du football | B10: Football : Fondamentaux | C10: 3
A11: Initiation aux fondamentaux du handball | B11: Handball : Fondamentaux | C11: 3
A12: Initiation aux fondamentaux de la gymnastique | B12: Gymnastique : Fondamentaux | C12: 2
A13: Initiation aux fondamentaux de l'athlétisme | B13: Fondamentaux des courses et des sauts | C13: 3
A14: Spécialisation théorique et pratique dans une APS | B14: APS de spécialité (choix d'un sport de spécialité) | C14: 3
A15: Techniques de communication écrite et orale | B15: ECUE 1 : Étude des styles de rédaction en langue française ; ECUE 2 : Anglais : vocabulaire du sport | C15: 4
B16: TOTAL Semestre 1 | C16: 30
A18: Semestre 2
A19: UE | B19: ECUE (contenu des enseignements) | C19: Crédits CECT/UE
A20: Sciences de la vie et de la santé | B20: ECUE 1 : Physiologie neuromusculaire, métabolisme et APS ; ECUE 2 : Physiologie des grandes fonctions | C20: 6
A21: Sciences humaines et sociales 1 | B21: ECUE 1 : Introduction à la sociologie ; ECUE 2 : Sociologie du jeu et des APS | C21: 4
A22: Initiation aux fondamentaux du rugby | B22: Rugby : Fondamentaux | C22: 3
A23: Initiation aux fondamentaux du basketball | B23: Basketball : Fondamentaux | C23: 3
A24: Initiation aux fondamentaux de la gymnastique II | B24: Gymnastique 2 : fondamentaux | C24: 3
A25: Initiation aux fondamentaux de l'athlétisme II | B25: Fondamentaux des courses de vitesse et des lancers | C25: 3
A26: Spécialisation théorique et pratique dans une APS | B26: APS de spécialité (choix d'un sport de spécialité) | C26: 3
A27: Initiation à l'environnement des TIC | B27: Formation à Microsoft Office Word | C27: 1
A28: Techniques de communication écrite et orale | B28: ECUE 1 : Anglais : communication orale (People and places) ; ECUE 2 : Français : expression orale et prise de parole en public | C28: 4
B29: TOTAL Semestre 2 | C29: 30
A31: Semestre 3
A32: UE | B32: ECUE (contenu des enseignements) | C32: Crédits CECT/UE
A33: Sciences de la vie et de la santé | B33: ECUE 1 : Nutrition et APS ; ECUE 2 : Biomécanique du geste | C33: 4
A34: Sciences humaines et sociales appliquées aux APS | B34: Histoire du sport : naissance et développement du sport moderne | C34: 2
A35: Connaissances institutionnelles du sport | B35: Connaissances institutionnelles et législatives de l'organisation du sport | C35: 2
A36: Initiation aux fondamentaux du volleyball | B36: Volleyball : Fondamentaux | C36: 3
A37: Initiation aux sports de combat de préhension | B37: Judo : Fondamentaux ; Lutte : Fondamentaux | C37: 2
A38: Initiation aux sports de combat de percussion | B38: Boxe : Fondamentaux ; Taekwondo : Fondamentaux | C38: 2
A39: Initiation aux sports d'entretien et santé | B39: Fitness et Conditionnement physique | C39: 2
A40: Matérialisation des plateaux de pratique des APS et performance | B40: Techniques de traçage des aires de pratique sportive et utilisation des instruments de mesure de la performance | C40: 3
A41: Spécialisation théorique et pratique dans une APS | B41: APS de spécialité (choix d'un sport de spécialité) | C41: 3
A42: Pré-professionnalisation | B42: Stage pédagogique au primaire : animation sportive 1re étape | C42: 3
A43: Techniques d'expression écrite et orale | B43: ECUE 1 : Anglais : communication orale (People and places : sport) ; ECUE 2 : Français : expression orale et prise de parole en public | C43: 4
B44: TOTAL Semestre 3 | C44: 30
A46: Semestre 4
A47: UE | B47: ECUE (contenu des enseignements) | C47: Crédits CECT/UE
A48: Connaissances historiques, sociologiques et institutionnelles du handicap | B48: ECUE 1 : Histoire et sociologie du handicap ; ECUE 2 : Santé publique et populations spécifiques (handicapés, personnes âgées) | C48: 4
A49: Biologie des populations spéciales | B49: ECUE 1 : Biologie des populations spéciales ; ECUE 2 : Biologie du vieillissement | C49: 4
A50: Rééducation fonctionnelle | B50: Pratique de la rééducation par les APA pour populations spécifiques 1 | C50: 2
A51: Intervention en milieu spécial | B51: ECUE 1 : Pratique des activités physiques par les déficients visuels et auditifs ; ECUE 2 : Pratique du fitness | C51: 5
A52: Prise en charge du handicap | B52: ECUE 1 : Pratique des activités physiques par les déficients visuels et auditifs ; ECUE 2 : Pratique du fitness | C52: 4
A53: Spécialisation théorique et pratique dans une APS | B53: APS de spécialité | C53: 2
A54: Pré-professionnalisation | B54: Stage dans un établissement d'accueil spécialisé dans le traitement des handicaps | C54: 3
A55: Méthodologie de la recherche | B55: Introduction à la méthodologie de la recherche scientifique | C55: 3
A56: Technologie de l'information et de la communication | B56: Initiation à l'informatique (bureautique) | C56: 1
A57: Technique d'expression écrite et orale | B57: Anglais professionnel spécifique aux APAS | C57: 2
B58: TOTAL Semestre 4 | C58: 30
A60: Semestre 5
A61: UE | B61: ECUE (contenu des enseignements) | C61: Crédits CECT/UE
A62: Sciences de la vie et de la santé et handicap | B62: ECUE 1 : Étiologie et physiopathologie des déficiences ; ECUE 2 : Analyse neuromusculaire de la posture et du mouvement | C62: 4
A63: Protocole de prise en charge par l'APA et déontologie | B63: ECUE 1 : APA : bilan et conduite pratique en rééducation ; ECUE 2 : Morale, éthique du care et bientraitance | C63: 4
A64: Diagnostic des incapacités et prise en charge des populations spéciales | B64: ECUE 1 : Rééducation par les APA pour populations spécifiques 2 ; ECUE 2 : Mesure et évaluation de la condition physique | C64: 6
A65: Prévention de la santé et traitement des pathologies par les APA | B65: ECUE 1 : Conditionnement physique et prévention des pathologies 1 ; ECUE 2 : Programmes d'APA les plus efficients dans le traitement de diverses pathologies | C65: 6
A66: Brevet National de Secourisme | B66: Préparation au BNS | C66: 2
A67: Spécialisation théorique et pratique dans une APS | B67: APS de spécialité | C67: 3
A68: Méthodologie et outils | B68: Méthodologie de la recherche scientifique : élaboration de projet de recherche | C68: 2
A69: Technique d'expression écrite et orale | B69: Anglais spécifique aux APAS | C69: 2
A70: Life Skills | B70: Culture civique | C70: 1
B71: TOTAL Semestre 5 | C71: 30
A73: Semestre 6
A74: UE | B74: ECUE (contenu des enseignements) | C74: Crédits CECT/UE
A75: Entrepreneuriat | B75: Développement communautaire en APA | C75: 2
A76: Relaxation et massage des populations spéciales | B76: Techniques de massages et de relaxation des populations spéciales | C76: 2
A77: Sciences de l'intervention en APAS | B77: Conception et planification des APA | C77: 3
A78: Prise en charge des populations spéciales 3 | B78: Rééducation par les APA pour populations spécifiques 3 | C78: 2
A79: Sciences et métiers de la prévention par les APS | B79: Programme d'Intégration, d'Équilibre Dynamique 1 (PIED) | C79: 3
A80: Prévention de la santé par le fitness | B80: Pratique du fitness et prévention des pathologies | C80: 3
A81: Spécialisation théorique et pratique dans une APS | B81: APS de spécialité | C81: 3
A82: Traumatologie du sport | B82: Pathologies liées à la pratique du sport et leurs traitements | C82: 2
A83: Pré-professionnalisation | B83: Stage dans une structure spécialisée dans la prise en charge des populations spéciales | C83: 4
A84: Formation à la recherche scientifique | B84: Séminaire de recherche : élaboration de projet de mémoire | C84: 3
A85: Technique d'expression écrite et orale | B85: Anglais spécifique aux APA | C85: 2
A86: Technologie de l'information et de la communication | B86: Conception et présentation des travaux avec PowerPoint | C86: 1
B87: TOTAL Semestre 6 | C87: 30
A89: TOTAL LICENCE : 180 crédits
A91: 🎓 PARCOURS MASTER
A92: Semestre 1 (M1/S7)
A93: UE | B93: ECUE (contenu des enseignements) | C93: Crédits CECT/UE
A94: Sciences de la vie et de la santé et APA | B94: ECUE 1 : Physiologie cardiovasculaire et activité physique ; ECUE 2 : Physiopathologie des maladies chroniques cardio-respiratoires et musculo-squelettiques | C94: 6
A95: Approche pratique du vieillissement | B95: Techniques de remise en condition physique des seniors : conditionnement en salle | C95: 3
A96: Évaluation de la condition physique des populations spéciales | B96: Tests d'évaluation de la condition physique des seniors | C96: 3
A97: Formation professionnelle | B97: Pratique du fitness par les populations spéciales | C97: 3
A98: Intervention en APA | B98: Variables de l'interaction dans la conduite des séances en APA | C98: 2
A99: Spécialisation théorique et pratique dans une APS | B99: APS de spécialité | C99: 3
A100: Méthodologie de la recherche | B100: Élaboration des instruments de collecte de données | C100: 4
A101: Formation à la recherche | B101: Séminaire de recherche | C101: 4
A102: Technique d'expression écrite et orale | B102: Anglais professionnel | C102: 2
B103: TOTAL Semestre 1 (M1/S7) | C103: 30
A105: Semestre 2 (M1/S8)
A106: UE | B106: ECUE (contenu des enseignements) | C106: Crédits CECT/UE
A107: Biomécanique et conditionnement musculaire | B107: ECUE 1 : Biomécanique appliquée au vieillissement et au handicap ; ECUE 2 : Vieillissement des systèmes cardiorespiratoire, nerveux et musculo-squelettique | C107: 4
A108: Nutrition et APA | B108: Alimentation et santé cardiovasculaire | C108: 2
A109: Approche pratique du vieillissement | B109: ECUE 1 : APA aux seniors : Programme PIED 2 ; ECUE 2 : Évaluation de la condition physique des populations spéciales | C109: 5
...

Sheet 5. Organisation
A1: STRUCTURE DE L'INSTITUT
A3: Sigle | B3: Intitulé / mission
A4: ENSEPS | B4: École Normale Supérieure de l'Éducation Physique et des Sports — filières STAPS (DER/STAPS)
A5: ENSEP | B5: École Normale Supérieure de l'Éducation Permanente — filières STASE (DER/STASE)
A6: CNSHN | B6: Centre National du Sport de Haut Niveau — détection et perfectionnement des athlètes
A7: CNMS | B7: Centre National de la Médecine du Sport — visites médicales, suivi médico-sportif
A8: DAAF | B8: Direction des Affaires Administratives et Financières
A9: DFCR | B9: Direction de la Formation Continue et de la Recherche — référentiels métiers
A10: DIEM | B10: Direction des Infrastructures, de l'Équipement et de la Maintenance
A11: DCP | B11: Direction de la Coopération et du Partenariat

Sheet 6. Groupes, Catég., Horaires
A1: 5. GROUPES — 6. CATÉGORIES — 12. PLAGES HORAIRES
A3: Rubrique | B3: Contenu
A4: Groupes | B4: Donnée interne non publiée, redéfinie à chaque rentrée. Organisation publique : groupes de cours/théorie (amphithéâtre) et groupes de pratique sportive ; groupe de spécialisation APS choisi dès le Semestre 2 ; filière PC-PS organisée par groupes-discipline (Basketball, Football, Handball, Volleyball, Athlétisme, Judo, Natation, Taekwondo, Rugby). Repères : 2 462 diplômés à la graduation 2026. Listes nominatives : scolarité DENSEPS/DENSEP.
A5: Catégories de cursus | B5: 1) Cursus universitaire (bacheliers, 5 ans) ; 2) Cycle professionnel (actifs, 2 ans) ; 3) Formation à la carte (communauté, courte durée).
A6: Catégories de concours 2025 | B6: PC-EPS, PC-PS, PC-EP, PC-EP-ENT (18-30 ans, BAC 2021-2025).
A7: Catégories de formations à la carte | B7: Sport ; Management ; Gestion ; Sécurité ; Artisanat ; Arts ; Business ; Agriculture ; Cuisine.
A8: Catégories d'APS enseignées | B8: Sports collectifs de grand terrain (football, rugby) ; de petit terrain (handball, basketball) ; de renvoi (volleyball) ; sports athlétiques ; sports de combat de préhension (judo, lutte) et de percussion (boxe, taekwondo) ; sports d'expression corporelle (gymnastique) ; sports d'entretien et APA (fitness, natation).
A9: Catégorie administrative | B9: Professeurs et inspecteurs formés : catégorie A de la fonction publique ivoirienne.
A10: Plages horaires | B10: Documents internes non publiés (variables chaque semestre). Cadre général : lundi-samedi ; matin ≈ 8h00-12h00 (cours magistraux) ; après-midi ≈ 14h00-18h00 (TD et pratique sportive sur plateaux : stades, gymnase, piscine, dojo) ; stages en structures partenaires. Précisions : scolarité de chaque école.

Sheet 7. Statistiques
A1: STATISTIQUES DES MAQUETTES OFFICIELLES
A2: Calculées à partir des 4 maquettes publiées (EM, MS, ES, APA). La répartition par famille de modules utilise une classification indicative.
A4: A. Détail par filière et par semestre
A5: Filière | B5: Palier | C5: Semestre | D5: Nb UE | E5: Nb ECUE | F5: Crédits
A6: EM | B6: Éducation et Motricité (EM) | C6: Licence | D6: Semestre 1 | E6: 9 | F6: 12 | G6: 30
A7: EM | B7: Éducation et Motricité (EM) | C7: Licence | D7: Semestre 2 | E7: 9 | F7: 12 | G7: 30
A8: EM | B8: Éducation et Motricité (EM) | C8: Licence | D8: Semestre 3 | E8: 11 | F8: 13 | G8: 30
A9: EM | B9: Éducation et Motricité (EM) | C9: Licence | D9: Semestre 4 | E9: 10 | F9: 12 | G9: 30
A10: EM | B10: Éducation et Motricité (EM) | C10: Licence | D10: Semestre 5 | E10: 11 | F10: 12 | G10: 30
A11: EM | B11: Éducation et Motricité (EM) | C11: Licence | D11: Semestre 6 | E11: 12 | F11: 12 | G11: 30
A12: EM | B12: Éducation et Motricité (EM) | C12: Master | D12: Semestre 1 (M1/S7) | E12: 9 | F12: 10 | G12: 30
A13: EM | B13: Éducation et Motricité (EM) | C13: Master | D13: Semestre 2 (M1/S8) | E13: 10 | F13: 11 | G13: 30
A14: EM | B14: Éducation et Motricité (EM) | C14: Master | D14: Semestre 3 (M2/S9) | E14: 3 | F14: 4 | G14: 30
A15: EM | B15: Éducation et Motricité (EM) | C15: Master | D15: Semestre 4 (M2/S10) | E15: 2 | F15: 2 | G15: 30
A16: MS | B16: Management du Sport (MS) | C16: Licence | D16: Semestre 1 | E16: 9 | F16: 12 | G16: 30
A17: MS | B17: Management du Sport (MS) | C17: Licence | D17: Semestre 2 | E17: 9 | F17: 12 | G17: 30
... A45: APA | B45: Activités Physiques Adaptées (APA) | C45: Master | D45: Semestre 4 (M2/S10) | E45: 2 | F45: 2 | G45: 30
A47: B. Répartition des crédits par famille de modules (classification indicative)
A48: Famille de modules | B48: EM | C48: MS | D48: ES | E48: APA | F48: Total
A49: Recherche & méthodologie | B49: 51 | C49: 44 | D49: 53 | E49: 51 | F49: 199
A50: Langues & communication | B50: 28 | C50: 20 | D50: 22 | E50: 22 | F50: 92
A51: TIC / bureautique | B51: 1 | C51: 4 | D51: 4 | E51: 9 | F51: 18
A52: Professionnalisation / stages | B52: 44 | C52: 42 | D52: 46 | E52: 48 | F52: 180
A53: Transversal / civique / secourisme | B53: 5 | C53: 3 | D53: 10 | E53: 7 | F53: 25
A54: EPS / didactique-pédagogie | B54: 82 | C54: 2 | D54: 2 | E54: 12 | F54: 98
A55: APA (activité physique adaptée) | B55: 0 | C55: 0 | D55: 0 | E55: 57 | F55: 57
A56: Entraînement sportif | B56: 0 | C56: 0 | D56: 58 | E56: 0 | F56: 58
A57: Management / droit / économie | B57: 0 | C57: 67 | D57: 0 | E57: 2 | F57: 69
A58: Sciences biomédicales | B58: 18 | C58: 16 | D58: 26 | E58: 22 | F58: 82
A59: Sciences humaines & sociales | B59: 20 | C59: 18 | D59: 16 | E59: 12 | F59: 66
A60: Pratiques sportives (APS) | B60: 51 | C60: 54 | D60: 63 | E60: 58 | F60: 226
A61: TOTAL | B61: 300 | C61: 270 | D61: 300 | E61: 300 | F61: 1170
A81: Semestre | B81: EM | C81: MS | D81: ES | E81: APA
A82: S1 | B82: 9 | C82: 9 | D82: 9 | E82: 9
A83: S2 | B83: 9 | C83: 9 | D83: 9 | E83: 9
A84: S3 | B84: 11 | C84: 11 | D84: 11 | E84: 11
A85: S4 | B85: 10 | C85: 10 | D85: 10 | E85: 10
A86: S5 | B86: 11 | C86: 11 | D86: 10 | E86: 9
A87: S6 | B87: 12 | C87: 9 | D87: 10 | E87: 12

Sheet 8. Base UE (source TCD)
A1: BASE DE DONNÉES NORMALISÉE DES ENSEIGNEMENTS (source d'analyse - ne pas modifier les en-têtes)
A3: Filière | B3: Filière (nom) | C3: École | D3: Palier | E3: Année | F3: Semestre | G3: UE | H3: ECUE (contenu) | I3: Nb ECUE | J3: Crédits | K3: Famille de modules | L3: Clé (Filière|Semestre|UE)
A4: EM | B4: Éducation et Motricité (EM) | C4: ENSEPS | D4: Licence | E4: L1 | F4: Semestre 1 | G4: Sciences de la vie et de la santé | H4: ECUE 1 : Anatomie descriptive du squelette appendiculaire ; ECUE 2 : Anatomie fonctionnelle du corps humain | I4: 2 | J4: 6 | K4: Sciences biomédicales | L4: EM|Semestre 1|Sciences de la vie et de la santé
A5: EM | B5: Éducation et Motricité (EM) | C5: ENSEPS | D5: Licence | E5: L1 | F5: Semestre 1 | G5: Sciences humaines et sociales | H5: ECUE 1 : Introduction à la psychologie générale ; ECUE 2 : Psychologie de l'apprentissage et du développement | I5: 2 | J5: 4 | K5: Sciences humaines & sociales | L5: EM|Semestre 1|Sciences humaines et sociales
A6: EM | B6: Éducation et Motricité (EM) | C6: ENSEPS | D6: Licence | E6: L1 | F6: Semestre 1 | G6: Sciences de l'intervention | H6: Concepts de base en intervention des APS | I6: 1 | J6: 2 | K6: EPS / didactique-pédagogie | L6: EM|Semestre 1|Sciences de l'intervention
A7: EM | B7: Éducation et Motricité (EM) | C7: ENSEPS | D7: Licence | E7: L1 | F7: Semestre 1 | G7: Initiation aux fondamentaux du football | H7: Football : Fondamentaux | I7: 1 | J7: 3 | K7: Pratiques sportives (APS) | L7: EM|Semestre 1|Initiation aux fondamentaux du football
A8: EM | B8: Éducation et Motricité (EM) | C8: ENSEPS | D8: Licence | E8: L1 | F8: Semestre 1 | G8: Initiation aux fondamentaux du handball | H8: Handball : Fondamentaux | I8: 1 | J8: 3 | K8: Pratiques sportives (APS) | L8: EM|Semestre 1|Initiation aux fondamentaux du handball
A9: EM | B9: Éducation et Motricité (EM) | C9: ENSEPS | D9: Licence | E9: L1 | F9: Semestre 1 | G9: Initiation aux fondamentaux de la gymnastique | H9: Gymnastique : Fondamentaux | I9: 1 | J9: 2 | K9: Pratiques sportives (APS) | L9: EM|Semestre 1|Initiation aux fondamentaux de la gymnastique
A10: EM | B10: Éducation et Motricité (EM) | C10: ENSEPS | D10: Licence | E10: L1 | F10: Semestre 1 | G10: Initiation aux fondamentaux de l'athlétisme | H10: Fondamentaux des courses et des sauts | I10: 1 | J10: 3 | K10: Pratiques sportives (APS) | L10: EM|Semestre 1|Initiation aux fondamentaux de l'athlétisme
A11: EM | B11: Éducation et Motricité (EM) | C11: ENSEPS | D11: Licence | E11: L1 | F11: Semestre 1 | G11: Spécialisation théorique et pratique dans une APS | H11: APS de spécialité (choix d'un sport de spécialité) | I11: 1 | J11: 3 | K11: Pratiques sportives (APS) | L11: EM|Semestre 1|Spécialisation théorique et pratique dans une APS
A12: EM | B12: Éducation et Motricité (EM) | C12: ENSEPS | D12: Licence | E12: L1 | F12: Semestre 1 | G12: Techniques de communication écrite et orale | H12: ECUE 1 : Étude des styles de rédaction en langue française ; ECUE 2 : Anglais : vocabulaire du sport | I12: 2 | J12: 4 | K12: Langues & communication | L12: EM|Semestre 1|Techniques de communication écrite et orale
A13: EM | B13: Éducation et Motricité (EM) | C13: ENSEPS | D13: Licence | E13: L1 | F13: Semestre 2 | G13: Sciences de la vie et de la santé | H13: ECUE 1 : Physiologie neuromusculaire, métabolisme et APS ; ECUE 2 : Physiologie des grandes fonctions | I13: 2 | J13: 6 | K13: Sciences biomédicales | L13: EM|Semestre 2|Sciences de la vie et de la santé
A14: EM | B14: Éducation et Motricité (EM) | C14: ENSEPS | D14: Licence | E14: L1 | F14: Semestre 2 | G14: Sciences humaines et sociales 1 | H14: ECUE 1 : Introduction à la sociologie ; ECUE 2 : Sociologie du jeu et des APS | I14: 2 | J14: 4 | K14: Sciences humaines & sociales | L14: EM|Semestre 2|Sciences humaines et sociales 1
A15: EM | B15: Éducation et Motricité (EM) | C15: ENSEPS | D15: Licence | E15: L1 | F15: Semestre 2 | G15: Initiation aux fondamentaux du rugby | H15: Rugby : Fondamentaux | I15: 1 | J15: 3 | K15: Pratiques sportives (APS) | L15: EM|Semestre 2|Initiation aux fondamentaux du rugby
... A326: APA | B326: Activités Physiques Adaptées (APA) | C326: ENSEPS | D326: Master | E326: M2 | F326: Semestre 4 (M2/S10) | G326: Formation professionnelle | H326: Stage milieu professionnel | I326: 1 | J326: 15 | K326: Professionnalisation / stages | L326: APA|Semestre 4 (M2/S10)|Formation professionnelle

Sheet 9. Analyse dynamique
A1: ANALYSES DYNAMIQUES (recalculées automatiquement depuis l'onglet « 8. Base UE »)
A2: Équivalent d'un tableau croisé dynamique : modifiez la base et les totaux se mettent à jour. Vous pouvez aussi créer un vrai TCD : Insertion > Tableau croisé dynamique sur la plage de la base.
A4: A. Crédits par filière x palier
A5: Filière | B5: Licence | C5: Master | D5: Total
A6: EM | B6: =SUMIFS('8. Base UE (source TCD)'!$J$4:$J$326,'8. Base UE (source TCD)'!$A$4:$A$326,$A6,'8. Base UE (source TCD)'!$D$4:$D$326,"Licence") | C6: =SUMIFS('8. Base UE (source TCD)'!$J$4:$J$326,'8. Base UE (source TCD)'!$A$4:$A$326,$A6,'8. Base UE (source TCD)'!$D$4:$D$326,"Master") | D6: =SUM(B6:C6)
A7: MS | B7: =SUMIFS('8. Base UE (source TCD)'!$J$4:$J$326,'8. Base UE (source TCD)'!$A$4:$A$326,$A7,'8. Base UE (source TCD)'!$D$4:$D$326,"Licence") | C7: =SUMIFS('8. Base UE (source TCD)'!$J$4:$J$326,'8. Base UE (source TCD)'!$A$4:$A$326,$A7,'8. Base UE (source TCD)'!$D$4:$D$326,"Master") | D7: =SUM(B7:C7)
A8: ES | B8: =SUMIFS('8. Base UE (source TCD)'!$J$4:$J$326,'8. Base UE (source TCD)'!$A$4:$A$326,$A8,'8. Base UE (source TCD)'!$D$4:$D$326,"Licence") | C8: =SUMIFS('8. Base UE (source TCD)'!$J$4:$J$326,'8. Base UE (source TCD)'!$A$4:$A$326,$A8,'8. Base UE (source TCD)'!$D$4:$D$326,"Master") | D8: =SUM(B8:C8)
A9: APA | B9: =SUMIFS('8. Base UE (source TCD)'!$J$4:$J$326,'8. Base UE (source TCD)'!$A$4:$A$326,$A9,'8. Base UE (source TCD)'!$D$4:$D$326,"Licence") | C9: =SUMIFS('8. Base UE (source TCD)'!$J$4:$J$326,'8. Base UE (source TCD)'!$A$4:$A$326,$A9,'8. Base UE (source TCD)'!$D$4:$D$326,"Master") | D9: =SUM(B9:C9)
A10: TOTAL | B10: =SUM(B6:B9) | C10: =SUM(C6:C9) | D10: =SUM(D6:D9)
A12: B. Nombre d'UE et d'ECUE par filière
A13: Filière | B13: Nb UE | C13: Nb ECUE
A14: EM | B14: =COUNTIFS('8. Base UE (source TCD)'!$A$4:$A$326,$A14) | C14: =SUMIFS('8. Base UE (source TCD)'!$I$4:$I$326,'8. Base UE (source TCD)'!$A$4:$A$326,$A14)
A15: MS | B15: =COUNTIFS('8. Base UE (source TCD)'!$A$4:$A$326,$A15) | C15: =SUMIFS('8. Base UE (source TCD)'!$I$4:$I$326,'8. Base UE (source TCD)'!$A$4:$A$326,$A15)
A16: ES | B16: =COUNTIFS('8. Base UE (source TCD)'!$A$4:$A$326,$A16) | C16: =SUMIFS('8. Base UE (source TCD)'!$I$4:$I$326,'8. Base UE (source TCD)'!$A$4:$A$326,$A16)
A17: APA | B17: =COUNTIFS('8. Base UE (source TCD)'!$A$4:$A$326,$A17) | C17: =SUMIFS('8. Base UE (source TCD)'!$I$4:$I$326,'8. Base UE (source TCD)'!$A$4:$A$326,$A17)
A19: C. Crédits par famille de modules x filière (classification indicative)
A20: Famille de modules | B20: EM | C20: MS | D20: ES | E20: APA | F20: Total
A21: Sciences biomédicales | B21: =SUMIFS('8. Base UE (source TCD)'!$J$4:$J$326,'8. Base UE (source TCD)'!$K$4:$K$326,$A21,'8. Base UE (source TCD)'!$A$4:$A$326,"EM") | C21: =SUMIFS('8. Base UE (source TCD)'!$J$4:$J$326,'8. Base UE (source TCD)'!$K$4:$K$326,$A21,'8. Base UE (source TCD)'!$A$4:$A$326,"MS") | D21: =SUMIFS('8. Base UE (source TCD)'!$J$4:$J$326,'8. Base UE (source TCD)'!$K$4:$K$326,$A21,'8. Base UE (source TCD)'!$A$4:$A$326,"ES") | E21: =SUMIFS('8. Base UE (source TCD)'!$J$4:$J$326,'8. Base UE (source TCD)'!$K$4:$K$326,$A21,'8. Base UE (source TCD)'!$A$4:$A$326,"APA") | F21: =SUM(B21:E21)
A22: Sciences humaines & sociales | B22: =SUMIFS('8. Base UE (source TCD)'!$J$4:$J$326,'8. Base UE (source TCD)'!$K$4:$K$326,$A22,'8. Base UE (source TCD)'!$A$4:$A$326,"EM") | C22: =SUMIFS('8. Base UE (source TCD)'!$J$4:$J$326,'8. Base UE (source TCD)'!$K$4:$K$326,$A22,'8. Base UE (source TCD)'!$A$4:$A$326,"MS") | D22: =SUMIFS('8. Base UE (source TCD)'!$J$4:$J$326,'8. Base UE (source TCD)'!$K$4:$K$326,$A22,'8. Base UE (source TCD)'!$A$4:$A$326,"ES") | E22: =SUMIFS('8. Base UE (source TCD)'!$J$4:$J$326,'8. Base UE (source TCD)'!$K$4:$K$326,$A22,'8. Base UE (source TCD)'!$A$4:$A$326,"APA") | F22: =SUM(B22:E22)
A23: EPS / didactique-pédagogie | B23: =SUMIFS('8. Base UE (source TCD)'!$J$4:$J$326,'8. Base UE (source TCD)'!$K$4:$K$326,$A23,'8. Base UE (source TCD)'!$A$4:$A$326,"EM") | C23: =SUMIFS('8. Base UE (source TCD)'!$J$4:$J$326,'8. Base UE (source TCD)'!$K$4:$K$326,$A23,'8. Base UE (source TCD)'!$A$4:$A$326,"MS") | D23: =SUMIFS('8. Base UE (source TCD)'!$J$4:$J$326,'8. Base UE (source TCD)'!$K$4:$K$326,$A23,'8. Base UE (source TCD)'!$A$4:$A$326,"ES") | E23: =SUMIFS('8. Base UE (source TCD)'!$J$4:$J$326,'8. Base UE (source TCD)'!$K$4:$K$326,$A23,'8. Base UE (source TCD)'!$A$4:$A$326,"APA") | F23: =SUM(B23:E23)
A24: Pratiques sportives (APS) | B24: =SUMIFS('8. Base UE (source TCD)'!$J$4:$J$326,'8. Base UE (source TCD)'!$K$4:$K$326,$A24,'8. Base UE (source TCD)'!$A$4:$A$326,"EM") | C24: =SUMIFS('8. Base UE (source TCD)'!$J$4:$J$326,'8. Base UE (source TCD)'!$K$4:$K$326,$A24,'8. Base UE (source TCD)'!$A$4:$A$326,"MS") | D24: =SUMIFS('8. Base UE (source TCD)'!$J$4:$J$326,'8. Base UE (source TCD)'!$K$4:$K$326,$A24,'8. Base UE (source TCD)'!$A$4:$A$326,"ES") | E24: =SUMIFS('8. Base UE (source TCD)'!$J$4:$J$326,'8. Base UE (source TCD)'!$K$4:$K$326,$A24,'8. Base UE (source TCD)'!$A$4:$A$326,"APA") | F24: =SUM(B24:E24)
A25: Langues & communication | B25: =SUMIFS('8. Base UE (source TCD)'!$J$4:$J$326,'8. Base UE (source TCD)'!$K$4:$K$326,$A25,'8. Base UE (source TCD)'!$A$4:$A$326,"EM") | C25: =SUMIFS('8. Base UE (source TCD)'!$J$4:$J$326,'8. Base UE (source TCD)'!$K$4:$K$326,$A25,'8. Base UE (source TCD)'!$A$4:$A$326,"MS") | D25: =SUMIFS('8. Base UE (source TCD)'!$J$4:$J$326,'8. Base UE (source TCD)'!$K$4:$K$326,$A25,'8. Base UE (source TCD)'!$A$4:$A$326,"ES") | E25: =SUMIFS('8. Base UE (source TCD)'!$J$4:$J$326,'8. Base UE (source TCD)'!$K$4:$K$326,$A25,'8. Base UE (source TCD)'!$A$4:$A$326,"APA") | F25: =SUM(B25:E25)
A26: TIC / bureautique | B26: =SUMIFS('8. Base UE (source TCD)'!$J$4:$J$326,'8. Base UE (source TCD)'!$K$4:$K$326,$A26,'8. Base UE (source TCD)'!$A$4:$A$326,"EM") | C26: =SUMIFS('8. Base UE (source TCD)'!$J$4:$J$326,'8. Base UE (source TCD)'!$K$4:$K$326,$A26,'8. Base UE (source TCD)'!$A$4:$A$326,"MS") | D26: =SUMIFS('8. Base UE (source TCD)'!$J$4:$J$326,'8. Base UE (source TCD)'!$K$4:$K$326,$A26,'8. Base UE (source TCD)'!$A$4:$A$326,"ES") | E26: =SUMIFS('8. Base UE (source TCD)'!$J$4:$J$326,'8. Base UE (source TCD)'!$K$4:$K$326,$A26,'8. Base UE (source TCD)'!$A$4:$A$326,"APA") | F26: =SUM(B26:E26)
A27: Professionnalisation / stages | B27: =SUMIFS('8. Base UE (source TCD)'!$J$4:$J$326,'8. Base UE (source TCD)'!$K$4:$K$326,$A27,'8. Base UE (source TCD)'!$A$4:$A$326,"EM") | C27: =SUMIFS('8. Base UE (source TCD)'!$J$4:$J$326,'8. Base UE (source TCD)'!$K$4:$K$326,$A27,'8. Base UE (source TCD)'!$A$4:$A$326,"MS") | D27: =SUMIFS('8. Base UE (source TCD)'!$J$4:$J$326,'8. Base UE (source TCD)'!$K$4:$K$326,$A27,'8. Base UE (source TCD)'!$A$4:$A$326,"ES") | E27: =SUMIFS('8. Base UE (source TCD)'!$J$4:$J$326,'8. Base UE (source TCD)'!$K$4:$K$326,$A27,'8. Base UE (source TCD)'!$A$4:$A$326,"APA") | F27: =SUM(B27:E27)
A28: Recherche & méthodologie | B28: =SUMIFS('8. Base UE (source TCD)'!$J$4:$J$326,'8. Base UE (source TCD)'!$K$4:$K$326,$A28,'8. Base UE (source TCD)'!$A$4:$A$326,"EM") | C28: =SUMIFS('8. Base UE (source TCD)'!$J$4:$J$326,'8. Base UE (source TCD)'!$K$4:$K$326,$A28,'8. Base UE (source TCD)'!$A$4:$A$326,"MS") | D28: =SUMIFS('8. Base UE (source TCD)'!$J$4:$J$326,'8. Base UE (source TCD)'!$K$4:$K$326,$A28,'8. Base UE (source TCD)'!$A$4:$A$326,"ES") | E28: =SUMIFS('8. Base UE (source TCD)'!$J$4:$J$326,'8. Base UE (source TCD)'!$K$4:$K$326,$A28,'8. Base UE (source TCD)'!$A$4:$A$326,"APA") | F28: =SUM(B28:E28)
A29: Transversal / civique / secourisme | B29: =SUMIFS('8. Base UE (source TCD)'!$J$4:$J$326,'8. Base UE (source TCD)'!$K$4:$K$326,$A29,'8. Base UE (source TCD)'!$A$4:$A$326,"EM") | C29: =SUMIFS('8. Base UE (source TCD)'!$J$4:$J$326,'8. Base UE (source TCD)'!$K$4:$K$326,$A29,'8. Base UE (source TCD)'!$A$4:$A$326,"MS") | D29: =SUMIFS('8. Base UE (source TCD)'!$J$4:$J$326,'8. Base UE (source TCD)'!$K$4:$K$326,$A29,'8. Base UE (source TCD)'!$A$4:$A$326,"ES") | E29: =SUMIFS('8. Base UE (source TCD)'!$J$4:$J$326,'8. Base UE (source TCD)'!$K$4:$K$326,$A29,'8. Base UE (source TCD)'!$A$4:$A$326,"APA") | F29: =SUM(B29:E29)
A30: Management / droit / économie | B30: =SUMIFS('8. Base UE (source TCD)'!$J$4:$J$326,'8. Base UE (source TCD)'!$K$4:$K$326,$A30,'8. Base UE (source TCD)'!$A$4:$A$326,"EM") | C30: =SUMIFS('8. Base UE (source TCD)'!$J$4:$J$326,'8. Base UE (source TCD)'!$K$4:$K$326,$A30,'8. Base UE (source TCD)'!$A$4:$A$326,"MS") | D30: =SUMIFS('8. Base UE (source TCD)'!$J$4:$J$326,'8. Base UE (source TCD)'!$K$4:$K$326,$A30,'8. Base UE (source TCD)'!$A$4:$A$326,"ES") | E30: =SUMIFS('8. Base UE (source TCD)'!$J$4:$J$326,'8. Base UE (source TCD)'!$K$4:$K$326,$A30,'8. Base UE (source TCD)'!$A$4:$A$326,"APA") | F30: =SUM(B30:E30)
A31: Entraînement sportif | B31: =SUMIFS('8. Base UE (source TCD)'!$J$4:$J$326,'8. Base UE (source TCD)'!$K$4:$K$326,$A31,'8. Base UE (source TCD)'!$A$4:$A$326,"EM") | C31: =SUMIFS('8. Base UE (source TCD)'!$J$4:$J$326,'8. Base UE (source TCD)'!$K$4:$K$326,$A31,'8. Base UE (source TCD)'!$A$4:$A$326,"MS") | D31: =SUMIFS('8. Base UE (source TCD)'!$J$4:$J$326,'8. Base UE (source TCD)'!$K$4:$K$326,$A31,'8. Base UE (source TCD)'!$A$4:$A$326,"ES") | E31: =SUMIFS('8. Base UE (source TCD)'!$J$4:$J$326,'8. Base UE (source TCD)'!$K$4:$K$326,$A31,'8. Base UE (source TCD)'!$A$4:$A$326,"APA") | F31: =SUM(B31:E31)
A32: APA (activité physique adaptée) | B32: =SUMIFS('8. Base UE (source TCD)'!$J$4:$J$326,'8. Base UE (source TCD)'!$K$4:$K$326,$A32,'8. Base UE (source TCD)'!$A$4:$A$326,"EM") | C32: =SUMIFS('8. Base UE (source TCD)'!$J$4:$J$326,'8. Base UE (source TCD)'!$K$4:$K$326,$A32,'8. Base UE (source TCD)'!$A$4:$A$326,"MS") | D32: =SUMIFS('8. Base UE (source TCD)'!$J$4:$J$326,'8. Base UE (source TCD)'!$K$4:$K$326,$A32,'8. Base UE (source TCD)'!$A$4:$A$326,"ES") | E32: =SUMIFS('8. Base UE (source TCD)'!$J$4:$J$326,'8. Base UE (source TCD)'!$K$4:$K$326,$A32,'8. Base UE (source TCD)'!$A$4:$A$326,"APA") | F32: =SUM(B32:E32)
A33: TOTAL | B33: =SUM(B21:B32) | C33: =SUM(C21:C32) | D33: =SUM(D21:D32) | E33: =SUM(E21:E32) | F33: =SUM(F21:F32)

Sheet Listes
A1: Cursus | B1: École | C1: Filière | D1: Sport de spécialité | E1: Année | F1: Statut | G1: Sexe | H1: Groupe | I1: Filière (code) | J1: Semestre | K1: Type de séance
A2: Cursus universitaire | B2: ENSEPS | C2: EM - Éducation et Motricité | D2: Football | E2: L1 | F2: Pré-inscrit | G2: M | H2: G1 | I2: EM | J2: Semestre 1 | K2: CM (cours magistral)
A3: Cycle professionnel | B3: ENSEP | C3: MS - Management du Sport | D3: Handball | E3: L2 | F3: Inscrit | G3: F | H3: G2 | I3: MS | J3: Semestre 2 | K3: TD (travaux dirigés)
A4: Formation à la carte | C4: ES - Entraînement Sportif | D4: Basketball | E4: L3 | F4: En cours | H4: G3 | I4: ES | J4: Semestre 3 | K4: TP / Pratique APS
A5: Concours professorat collège | C5: APA - Activités Physiques Adaptées | D5: Rugby | E5: M1 | F5: Admis(e) | H5: G4 | I5: APA | J5: Semestre 4 | K5: Stage
C6: Andragogie | D6: Volleyball | E6: M2 | F6: Redouble | H6: G5 | J6: Semestre 5 | K6: Évaluation
C7: Loisir | D7: Athlétisme | E7: Année 1 (cycle pro) | F7: Ajourné(e) | H7: G6 | J7: Semestre 6 | K7: Séminaire de recherche
C8: ECJP - Entrepreneuriat Jeunesse et Conduite de Projets | D8: Judo | E8: Année 2 (cycle pro) | F8: Exclu(e) | J8: Semestre 1 (M1/S7) | K8: Autre
C9: Gérontologie | D9: Lutte | E9: Autre | F9: Diplômé(e) | J9: Semestre 2 (M1/S8)
C10: PC-EPS | D10: Boxe | F10: Abandon | J10: Semestre 3 (M2/S9)
C11: PC-EP | D11: Taekwondo | J11: Semestre 4 (M2/S10)
C12: PC-EP-ENT | D12: Natation
C13: PC-PS | D13: Gymnastique
C14: Maîtrise d'EPS | D14: Fitness
C15: Conseillat d'EPS
C16: Professorat professionnel d'EPS
C17: Inspectorat J&S
C18: Inspectorat pédagogique
C19: Agrégation
C20: Maîtrise adjointe d'EP
C21: Maîtrise d'EP
C22: Conseillat d'EP
C23: Professorat professionnel d'EP

Sheet 10. Suivi inscriptions
A1: FORMULAIRE DE SUIVI DES INSCRIPTIONS / SCOLARITÉ — INJS (modèle prêt à l'emploi)
A2: Colonnes avec listes déroulantes pré-configurées. Dupliquez les lignes selon vos besoins. Le code matricule suggéré : INJS-ANNEE-FILIERE-N°ordre (ex. INJS-2026-EM-001).
A4: N° | B4: Matricule | C4: Nom | D4: Prénoms | E4: Date de naissance | F4: Sexe | G4: Nationalité | H4: Téléphone | I4: Email | J4: Cursus | K4: École | L4: Filière | M4: Sport de spécialité | N4: Année | O4: Groupe | P4: Contact parent/tuteur | Q4: Statut | R4: Observations
A5: 1
A6: 2
A7: 3
A8: 4
A9: 5
A10: 6
A11: 7
A12: 8
A13: 9
A14: 10
A15: 11
A16: 12
... A204: 200

Sheet 11. Suivi des notes
A1: SUIVI DES NOTES ET MOYENNES PAR UE — saisie longue (1 ligne = 1 étudiant × 1 UE)
A2: Filière / Semestre / UE : listes déroulantes. Les crédits de l'UE se remplissent automatiquement (recherche dans la base officielle). Pondération CC/Examen paramétrable ci-dessous (à ajuster selon le règlement des études de l'INJS). | E2: Poids contrôle continu : | F2: 0.4 | H2: Poids examen : | I2: 0.6
A4: N° | B4: Matricule | C4: Nom | D4: Prénoms | E4: Filière | F4: Semestre | G4: UE | H4: Clé (auto) | I4: Crédits (auto) | J4: Note CC /20 | K4: Note Examen /20 | L4: Moyenne UE /20 (auto) | M4: Points crédités (auto)
A5: 1 | H5: =IF(OR(E5="",F5="",G5=""),"",E5&"|"&F5&"|"&G5) | I5: =IFERROR(INDEX('8. Base UE (source TCD)'!$J$4:$J$326,MATCH(H5,'8. Base UE (source TCD)'!$L$4:$L$326,0)),"") | L5: =IF(COUNT(J5:K5)=0,"",ROUND(J5*$F$2+K5*$I$2,2)) | M5: =IF(L5="","",L5*I5)
A6: 2 | H6: =IF(OR(E6="",F6="",G6=""),"",E6&"|"&F6&"|"&G6) | I6: =IFERROR(INDEX('8. Base UE (source TCD)'!$J$4:$J$326,MATCH(H6,'8. Base UE (source TCD)'!$L$4:$L$326,0)),"") | L6: =IF(COUNT(J6:K6)=0,"",ROUND(J6*$F$2+K6*$I$2,2)) | M6: =IF(L6="","",L6*I6)
A7: 3 | H7: =IF(OR(E7="",F7="",G7=""),"",E7&"|"&F7&"|"&G7) | I7: =IFERROR(INDEX('8. Base UE (source TCD)'!$J$4:$J$326,MATCH(H7,'8. Base UE (source TCD)'!$L$4:$L$326,0)),"") | L7: =IF(COUNT(J7:K7)=0,"",ROUND(J7*$F$2+K7*$I$2,2)) | M7: =IF(L7="","",L7*I7)
A8: 4 | H8: =IF(OR(E8="",F8="",G8=""),"",E8&"|"&F8&"|"&G8) | I8: =IFERROR(INDEX('8. Base UE (source TCD)'!$J$4:$J$326,MATCH(H8,'8. Base UE (source TCD)'!$L$4:$L$326,0)),"") | L8: =IF(COUNT(J8:K8)=0,"",ROUND(J8*$F$2+K8*$I$2,2)) | M8: =IF(L8="","",L8*I8)
A9: 5 | H9: =IF(OR(E9="",F9="",G9=""),"",E9&"|"&F9&"|"&G9) | I9: =IFERROR(INDEX('8. Base UE (source TCD)'!$J$4:$J$326,MATCH(H9,'8. Base UE (source TCD)'!$L$4:$L$326,0)),"") | L9: =IF(COUNT(J9:K9)=0,"",ROUND(J9*$F$2+K9*$I$2,2)) | M9: =IF(L9="","",L9*I9)
A10: 6 | H10: =IF(OR(E10="",F10="",G10=""),"",E10&"|"&F10&"|"&G10) | I10: =IFERROR(INDEX('8. Base UE (source TCD)'!$J$4:$J$326,MATCH(H10,'8. Base UE (source TCD)'!$L$4:$L$326,0)),"") | L10: =IF(COUNT(J10:K10)=0,"",ROUND(J10*$F$2+K10*$I$2,2)) | M10: =IF(L10="","",L10*I10)
A11: 7 | H11: =IF(OR(E11="",F11="",G11=""),"",E11&"|"&F11&"|"&G11) | I11: =IFERROR(INDEX('8. Base UE (source TCD)'!$J$4:$J$326,MATCH(H11,'8. Base UE (source TCD)'!$L$4:$L$326,0)),"") | L11: =IF(COUNT(J11:K11)=0,"",ROUND(J11*$F$2+K11*$I$2,2)) | M11: =IF(L11="","",L11*I11)
A12: 8 | H12: =IF(OR(E12="",F12="",G12=""),"",E12&"|"&F12&"|"&G12) | I12: =IFERROR(INDEX('8. Base UE (source TCD)'!$J$4:$J$326,MATCH(H12,'8. Base UE (source TCD)'!$L$4:$L$326,0)),"") | L12: =IF(COUNT(J12:K12)=0,"",ROUND(J12*$F$2+K12*$I$2,2)) | M12: =IF(L12="","",L12*I12)
A13: 9 | H13: =IF(OR(E13="",F13="",G13=""),"",E13&"|"&F13&"|"&G13) | I13: =IFERROR(INDEX('8. Base UE (source TCD)'!$J$4:$J$326,MATCH(H13,'8. Base UE (source TCD)'!$L$4:$L$326,0)),"") | L13: =IF(COUNT(J13:K13)=0,"",ROUND(J13*$F$2+K13*$I$2,2)) | M13: =IF(L13="","",L13*I13)
A14: 10 | H14: =IF(OR(E14="",F14="",G14=""),"",E14&"|"&F14&"|"&G14) | I14: =IFERROR(INDEX('8. Base UE (source TCD)'!$J$4:$J$326,MATCH(H14,'8. Base UE (source TCD)'!$L$4:$L$326,0)),"") | L14: =IF(COUNT(J14:K14)=0,"",ROUND(J14*$F$2+K14*$I$2,2)) | M14: =IF(L14="","",L14*I14)
A15: 11 | H15: =IF(OR(E15="",F15="",G15=""),"",E15&"|"&F15&"|"&G15) | I15: =IFERROR(INDEX('8. Base UE (source TCD)'!$J$4:$J$326,MATCH(H15,'8. Base UE (source TCD)'!$L$4:$L$326,0)),"") | L15: =IF(COUNT(J15:K15)=0,"",ROUND(J15*$F$2+K15*$I$2,2)) | M15: =IF(L15="","",L15*I15)
A16: 12 | H16: =IF(OR(E16="",F16="",G16=""),"",E16&"|"&F16&"|"&G16) | I16: =IFERROR(INDEX('8. Base UE (source TCD)'!$J$4:$J$326,MATCH(H16,'8. Base UE (source TCD)'!$L$4:$L$326,0)),"") | L16: =IF(COUNT(J16:K16)=0,"",ROUND(J16*$F$2+K16*$I$2,2)) | M16: =IF(L16="","",L16*I16)
... A304: 300 | H304: =IF(OR(E304="",F304="",G304=""),"",E304&"|"&F304&"|"&G304) | I304: =IFERROR(INDEX('8. Base UE (source TCD)'!$J$4:$J$326,MATCH(H304,'8. Base UE (source TCD)'!$L$4:$L$326,0)),"") | L304: =IF(COUNT(J304:K304)=0,"",ROUND(J304*$F$2+K304*$I$2,2)) | M304: =IF(L304="","",L304*I304)

Sheet 12. Relevé de notes
A1: RELEVÉ DE NOTES ET DÉCISION PAR ÉTUDIANT (calculé depuis l'onglet « 11. Suivi des notes »)
A3: Matricule de l'étudiant :
A5: Nom et prénoms : | B5: =IFERROR(INDEX('11. Suivi des notes'!$C$5:$C$304&" "&'11. Suivi des notes'!$D$5:$D$304,MATCH($B$3,'11. Suivi des notes'!$B$5:$B$304,0)),"")
A6: Crédits inscrits : | B6: =IFERROR(SUMIFS('11. Suivi des notes'!$I$5:$I$304,'11. Suivi des notes'!$B$5:$B$304,$B$3),0)
A7: Points obtenus : | B7: =IFERROR(SUMIFS('11. Suivi des notes'!$M$5:$M$304,'11. Suivi des notes'!$B$5:$B$304,$B$3),0)
A8: Moyenne générale /20 : | B8: =IF(B6=0,"",ROUND(B7/B6,2))
A9: UE validées (>= 10) : | B9: =COUNTIFS('11. Suivi des notes'!$B$5:$B$304,$B$3,'11. Suivi des notes'!$L$5:$L$304,">=10")
A10: UE non validées (< 10) : | B10: =COUNTIFS('11. Suivi des notes'!$B$5:$B$304,$B$3,'11. Suivi des notes'!$L$5:$L$304,"<10")
A11: DÉCISION : | B11: =IF(B8="","",IF(B8>=10,"SEMESTRE VALIDÉ","NON VALIDÉ"))
D14: Rappel barème : moyenne UE = Note CC x poids CC + Note Examen x poids examen (poids modifiables dans l'onglet 11). Seuil de validation = 10/20 (règle LMD classique — à confirmer avec le règlement intérieur de l'INJS).

Sheet 13. Emploi du temps (modèle)
A1: EMPLOI DU TEMps — MODÈLE VIERGE (hebdomadaire)
B3: Filière : | E3: Année : | H3: Groupe : | K3: Semestre :
B4: Semaine du : | E4: Enseignant(s) :
A7: Plage horaire | B7: Lundi | C7: Mardi | D7: Mercredi | E7: Jeudi | F7: Vendredi | G7: Samedi
A8: 07h30 - 09h30
A10: 09h45 - 11h45
A12: 13h30 - 15h30
A14: 15h45 - 17h45
A18: Lecture : ligne 1 de chaque plage = UE / activité ; ligne 2 = type de séance (liste déroulante) + salle/plateau. Pause méridienne ~ 11h45-13h30. Modèle neutre à adapter aux horaires officiels communiqués par la scolarité.
